a2abase_cli/__init__.py
a2abase_cli/cli.py
a2abase_cli/commands/__init__.py
a2abase_cli/commands/add.py
a2abase_cli/commands/dev.py
a2abase_cli/commands/doctor.py
a2abase_cli/commands/init.py
a2abase_cli/commands/run.py
a2abase_cli/commands/test.py
a2abase_cli/commands/version.py
a2abase_cli/generators/__init__.py
a2abase_cli/generators/agent.py
a2abase_cli/generators/project.py
a2abase_cli/generators/shared.py
a2abase_cli/generators/tool.py
a2abase_cli-0.1.7.dist-info/METADATA
a2abase_cli-0.1.7.dist-info/WHEEL
a2abase_cli-0.1.7.dist-info/entry_points.txt
a2abase_cli-0.1.7.dist-info/RECORD
