Metadata-Version: 2.4
Name: a2abase-cli
Version: 0.1.7
Summary: Production-ready CLI tool for scaffolding A2ABase Agent SDK projects
Project-URL: Homepage, https://github.com/A2ABaseAI/sdks
Project-URL: Repository, https://github.com/A2ABaseAI/sdks
Project-URL: Issues, https://github.com/A2ABaseAI/sdks/issues
Author: BelArabyAI
License: MIT
Keywords: a2abase,agent,cli,scaffold,sdk
Classifier: Development Status :: 4 - Beta
Classifier: Intended Audience :: Developers
Classifier: License :: OSI Approved :: MIT License
Classifier: Programming Language :: Python :: 3
Classifier: Programming Language :: Python :: 3.11
Classifier: Programming Language :: Python :: 3.12
Requires-Python: >=3.11
Requires-Dist: jinja2>=3.1.4
Requires-Dist: pydantic>=2.8.0
Requires-Dist: pyyaml>=6.0.1
Requires-Dist: rich>=13.7.0
Requires-Dist: typer>=0.12.0
Requires-Dist: watchfiles>=0.24.0
Provides-Extra: dev
Requires-Dist: pytest-asyncio>=0.23.0; extra == 'dev'
Requires-Dist: pytest-cov>=7.0.0; extra == 'dev'
Requires-Dist: pytest>=8.0.0; extra == 'dev'
Requires-Dist: ruff>=0.6.0; extra == 'dev'
Provides-Extra: ngrok
Requires-Dist: pyngrok>=7.0.0; extra == 'ngrok'
